mkdocs_gds/404.html
mkdocs_gds/__init__.py
mkdocs_gds/base.html
mkdocs_gds/content.html
mkdocs_gds/keyboard-modal.html
mkdocs_gds/main.html
mkdocs_gds/mkdocs_theme.yml
mkdocs_gds/nav-sub.html
mkdocs_gds/side_nav.html
mkdocs_gds/toc.html
mkdocs_gds/assets/fonts/bold-affa96571d-v2.woff
mkdocs_gds/assets/fonts/bold-b542beb274-v2.woff2
mkdocs_gds/assets/fonts/light-94a07e06a1-v2.woff2
mkdocs_gds/assets/fonts/light-f591b13f7d-v2.woff
mkdocs_gds/assets/images/favicon.ico
mkdocs_gds/assets/images/govuk-apple-touch-icon-152x152.png
mkdocs_gds/assets/images/govuk-apple-touch-icon-167x167.png
mkdocs_gds/assets/images/govuk-apple-touch-icon-180x180.png
mkdocs_gds/assets/images/govuk-apple-touch-icon.png
mkdocs_gds/assets/images/govuk-crest-2x.png
mkdocs_gds/assets/images/govuk-crest.png
mkdocs_gds/assets/images/govuk-logotype-crown.png
mkdocs_gds/assets/images/govuk-mask-icon.svg
mkdocs_gds/assets/images/govuk-opengraph-image.png
mkdocs_gds/css/all-ie8.css
mkdocs_gds/css/base.css
mkdocs_gds/fonts/fontawesome-webfont.eot
mkdocs_gds/fonts/fontawesome-webfont.svg
mkdocs_gds/fonts/fontawesome-webfont.ttf
mkdocs_gds/fonts/fontawesome-webfont.woff
mkdocs_gds/fonts/fontawesome-webfont.woff2
mkdocs_gds/img/favicon.ico
mkdocs_gds/img/grid.png
mkdocs_gds/js/all.js
mkdocs_gds/js/bootstrap.min.js
mkdocs_gds/js/jquery-1.10.2.min.js
mkdocs_gds/js/search/search-bar.js
mkdocs_gds/js/search/simple-search.js
src/__init__.py
mkdocs_gds-0.0.9.dist-info/LICENSE
mkdocs_gds-0.0.9.dist-info/METADATA
mkdocs_gds-0.0.9.dist-info/WHEEL
mkdocs_gds-0.0.9.dist-info/entry_points.txt
mkdocs_gds-0.0.9.dist-info/top_level.txt
mkdocs_gds-0.0.9.dist-info/RECORD
